{
    "id": "preferred_seat_booking",
    "benefitType": "feature",
    "displayGroup": "travel",
    "localized": {
        "en": {
            "name": "Select a preferred seat at booking",
            "description": null
        }
    },
    "value": 35,
    "valueCurrency": "USD",
    "frequency": "ongoing",
    "isRecurring": true,
    "trackingMode": "manual",
    "requiresActivation": false,
    "partnerName": "Southwest",
    "redemptionMethod": "automatic",
    "displayOrder": 0,
    "isActive": true
}
